{
  "speakers": {
    "npc": {
      "name": "     ",
      "face": {
        "type": "artificial",
        "modelType": "npc",
        "identifier": "cobblemon:supernerd",
        "isLeftSide": true
      }
    }
  },
  "pages": [
    {
      "id": "greeting",
      "speaker": "npc",
      "lines": [
        "Making a large ship is more like constructing a building than assembling a vehicle."
      ],
      "input": {
        "type": "option",
        "vertical": false,
        "options": [
          {
            "text": "Close",
            "value": "close",
            "action": [
              "q.dialogue.close();"
            ]
          }
        ]
      }
    }
  ]
}