{
  "speakers": {
    "npc": {
      "name": "     ",
      "face": {
        "type": "artificial",
        "modelType": "npc",
        "identifier": "cobblemon:schoolboy",
        "isLeftSide": true
      }
    }
  },
  "pages": [
    {
      "id": "greeting",
      "speaker": "npc",
      "lines": [
        "At this art museum...well, you can see many fantastic paintings."
      ],
      "input": {
        "type": "option",
        "vertical": false,
        "options": [
          {
            "text": "Next",
            "value": "next",
            "action": "q.dialogue.set_page('page2');"
          }
        ]
      }
    },
    {
      "id": "page2",
      "speaker": "npc",
      "lines": [
        "And the curator is a wonderful person."
      ],
      "input": {
        "type": "option",
        "vertical": false,
        "options": [
          {
            "text": "Next",
            "value": "next",
            "action": "q.dialogue.set_page('page3');"
          }
        ]
      }
    },
    {
      "id": "page3",
      "speaker": "npc",
      "lines": [
        "Among artists like myself, this museum is an inspiration."
      ],
      "input": {
        "type": "option",
        "vertical": false,
        "options": [
          {
            "text": "Close",
            "value": "close",
            "action": [
              "q.dialogue.close();"
            ]
          }
        ]
      }
    }
  ]
}