{
  "hitbox": "player",
  "resourceIdentifier": "cobblemon:steven",
  "presets": [
    "cobblemon:trainer_basics"
  ],
  "interaction": {
    "type": "dialogue",
    "dialogue": "cobblemon:rematch_steven_interaction"
  },
  "name": "Steven",
  "party": {
    "type": "simple",
    "pokemon": [
      "Skarmory level=77",
      "Claydol level=77",
      "Aggron level=77",
      "Carbink level=77",
      "Aerodactyl level=77",
      "Metagross level=79"
    ]
  },
  "config": [
    {
      "variableName": "challenge_cooldown",
      "displayName": "Cooldown",
      "description": "How long in ticks the NPC will be un-challengable from that player's last challenge.",
      "type": "NUMBER",
      "defaultValue": "0"
    },
    {
      "variableName": "can_rechallenge",
      "displayName": "Rechallenging",
      "description": "This NPC can be battled multiple times.",
      "type": "BOOLEAN",
      "defaultValue": true
    },
    {
      "variableName": "on_player_wins",
      "displayName": "npc.variable.on_player_wins.name",
      "description": "npc.variable.on_player_wins.desc",
      "type": "TEXT",
      "defaultValue": "q.run_command('execute as ' + q.player.username + ' run opendialogue rematch_steven_end @s');"
    }
  ]
}