{
  "speakers": {
    "npc": {
      "name": "     ",
      "face": {
        "type": "artificial",
        "modelType": "npc",
        "identifier": "cobblemon:youngster",
        "isLeftSide": true
      }
    }
  },
  "pages": [
    {
      "id": "greeting",
      "speaker": "npc",
      "lines": [
        "If you step into the tall grass on the route up ahead, wild Pokémon will jump out at you!"
      ],
      "input": {
        "type": "option",
        "vertical": false,
        "options": [
          {
            "text": "Next",
            "value": "next",
            "action": "q.dialogue.set_page('page2');"
          }
        ]
      }
    },
    {
      "id": "page2",
      "speaker": "npc",
      "lines": [
        "It's not safe to go out there if you don't have any Pokémon with you."
      ],
      "input": {
        "type": "option",
        "vertical": false,
        "options": [
          {
            "text": "Close",
            "value": "close",
            "action": [
              "q.dialogue.close();"
            ]
          }
        ]
      }
    }
  ]
}